colortheme/__init__.py
colortheme/py.typed
colortheme/assets/script_templates/getStartIcon.js
colortheme/assets/script_templates/getWallpaper.js
colortheme/assets/script_templates/setStartIcon.js
colortheme/assets/script_templates/setWallpaper.js
colortheme/cli/__init__.py
colortheme/cli/entry_point.py
colortheme/context/__init__.py
colortheme/context/context.py
colortheme/main/__init__.py
colortheme/main/eventchecker.py
colortheme/main/main.py
colortheme/main/sun_hours.py
colortheme/main/thememanager.py
colortheme/models/__init__.py
colortheme/models/action.py
colortheme/models/config.py
colortheme/models/options.py
colortheme/models/path.py
colortheme/models/secrets_.py
colortheme-0.1.1.dist-info/LICENSE
colortheme-0.1.1.dist-info/METADATA
colortheme-0.1.1.dist-info/WHEEL
colortheme-0.1.1.dist-info/entry_points.txt
colortheme-0.1.1.dist-info/top_level.txt
colortheme-0.1.1.dist-info/RECORD
