Metadata-Version: 2.1
Name: colortheme
Version: 0.1.1
Summary: Automate color theme configuration based on time of the day
Author-email: Quinten Roets <qdr2104@columbia.edu>
License: MIT
Project-URL: Source Code, https://github.com/quintenroets/colortheme
Requires-Python: >=3.10
License-File: LICENSE
Requires-Dist: astral <4,>=3.2
Requires-Dist: backupmaster <2,>=1.2.10
Requires-Dist: geocoder <2,>=1.38.1
Provides-Extra: dev
Requires-Dist: package-dev-tools <1,>=0.5.11 ; extra == 'dev'
Requires-Dist: package-dev-utils <1,>=0.1.6 ; extra == 'dev'
